pytorchures/__init__.py
pytorchures/run_profiling.py
pytorchures/timing.py
pytorchures/torchvision_pipeline.py
pytorchures-0.1.2.dist-info/LICENSE
pytorchures-0.1.2.dist-info/METADATA
pytorchures-0.1.2.dist-info/WHEEL
pytorchures-0.1.2.dist-info/top_level.txt
pytorchures-0.1.2.dist-info/RECORD
