Metadata-Version: 2.1
Name: pytorchures
Version: 0.1.2
Summary: Measure execution times of every layer in your pytorch model.
License: Copyright (c) 2024 Cezary Bloch
Project-URL: Homepage, https://github.com/cezbloch/pytorchures
Keywords: pytorch,performance,layers,profiling
Classifier: License :: OSI Approved :: MIT License
Classifier: Programming Language :: Python
Classifier: Programming Language :: Python :: 3
Classifier: Programming Language :: Python :: 3.9
Classifier: Programming Language :: Python :: 3.10
Classifier: Programming Language :: Python :: 3.11
Classifier: Programming Language :: Python :: 3.12
Requires-Python: >=3.9
License-File: LICENSE
Requires-Dist: torch<3,>=2
Requires-Dist: torchvision<1,>=0.18
Provides-Extra: dev
Requires-Dist: black; extra == "dev"
Requires-Dist: isort; extra == "dev"
Requires-Dist: pytest; extra == "dev"
Requires-Dist: flake8; extra == "dev"
Requires-Dist: mypy; extra == "dev"
Provides-Extra: publish
Requires-Dist: build; extra == "publish"
Requires-Dist: twine; extra == "publish"
